[
    {
        "text": "Uma serpente emplumada com a cola de chupeta",
        "image": "",
        "key": 0
    },
    {
        "text": "A arte e a ciência",
        "image": "",
        "key": 1
    },
    {
        "text": "A ciência da arte",
        "image": "",
        "key": 2
    },
    {
        "text": "E teu amor com o meu",
        "image": "",
        "key": 3
    },
    {
        "text": "Companheiro vivo",
        "image": "",
        "key": 4
    },
    {
        "text": "Navegando vivos",
        "image": "",
        "key": 5
    },
    {
        "text": "Juntos este rio",
        "image": "",
        "key": 6
    },
    {
        "text": "Rimos choramos",
        "image": "",
        "key": 7
    },
    {
        "text": "Pensamos sabemos",
        "image": "",
        "key": 8
    },
    {
        "text": "Sofremos por isto",
        "image": "",
        "key": 9
    },
    {
        "text": "Nascer é uma festa",
        "image": "",
        "key": 10
    },
    {
        "text": "Quiçá teu delírio",
        "image": "",
        "key": 11
    },
    {
        "text": "Seja como o meu",
        "image": "",
        "key": 12
    },
    {
        "text": "Nada mais que vivos",
        "image": "",
        "key": 13
    },
    {
        "text": "E amando muito",
        "image": "",
        "key": 14
    },
    {
        "text": "Desprezando-nos para reapreciar-nos",
        "image": "",
        "key": 15
    },
    {
        "text": "À vez que às vezes",
        "image": "",
        "key": 16
    },
    {
        "text": "É sempre a mesma",
        "image": "",
        "key": 17
    },
    {
        "text": "Este pano roxo",
        "image": "",
        "key": 18
    },
    {
        "text": "Tingido com sangue",
        "image": "",
        "key": 19
    },
    {
        "text": "Escrito com ouro",
        "image": "",
        "key": 20
    },
    {
        "text": "Pedaço dum sol",
        "image": "",
        "key": 21
    },
    {
        "text": "Trágicos meteoros",
        "image": "",
        "key": 22
    },
    {
        "text": "Com a cola de chupeta",
        "image": "",
        "key": 23
    },
    {
        "text": "É dura a vida",
        "image": "",
        "key": 24
    },
    {
        "text": "Que igual vivemos",
        "image": "",
        "key": 25
    },
    {
        "text": "Quase que sabemos",
        "image": "",
        "key": 26
    },
    {
        "text": "Isto não vai mais",
        "image": "",
        "key": 27
    },
    {
        "text": "Gozamos nós",
        "image": "",
        "key": 28
    },
    {
        "text": "Porque assim nascemos",
        "image": "",
        "key": 29
    },
    {
        "text": "Todo filho é gozo",
        "image": "",
        "key": 30
    },
    {
        "text": "Pais de esperanças",
        "image": "",
        "key": 31
    },
    {
        "text": "Anelos viventes",
        "image": "",
        "key": 32
    },
    {
        "text": "Nosso porvir",
        "image": "",
        "key": 33
    },
    {
        "text": "Somos alquimistas",
        "image": "",
        "key": 34
    },
    {
        "text": "Universo cultivamos",
        "image": "",
        "key": 35
    },
    {
        "text": "Como nos olhamos",
        "image": "",
        "key": 36
    },
    {
        "text": "Um é do outro",
        "image": "",
        "key": 37
    },
    {
        "text": "Outro assentimento",
        "image": "",
        "key": 38
    },
    {
        "text": "Quanto nos queremos",
        "image": "",
        "key": 39
    },
    {
        "text": "Quanto é que podemos",
        "image": "",
        "key": 40
    },
    {
        "text": "Muito pouco sabemos",
        "image": "",
        "key": 41
    },
    {
        "text": "Quem poderia dizer",
        "image": "",
        "key": 42
    },
    {
        "text": "Até onde poderíamos",
        "image": "",
        "key": 43
    },
    {
        "text": "Podemos até onde vamos",
        "image": "",
        "key": 44
    },
    {
        "text": "Desejamos encontrar-nos",
        "image": "",
        "key": 45
    },
    {
        "text": "Necessariamente Extraviados",
        "image": "",
        "key": 46
    },
    {
        "text": "É nossa necessidade",
        "image": "",
        "key": 47
    },
    {
        "text": "Por afirmar-nos mutuamente",
        "image": "",
        "key": 48
    },
    {
        "text": "Na afirmação",
        "image": "",
        "key": 49
    },
    {
        "text": "Do amor necessário",
        "image": "",
        "key": 50
    },
    {
        "text": "Colossal teatro",
        "image": "",
        "key": 51
    },
    {
        "text": "Vogando na duração",
        "image": "",
        "key": 52
    },
    {
        "text": "É uma arte viver",
        "image": "",
        "key": 53
    },
    {
        "text": "Para nós artistas",
        "image": "",
        "key": 54
    },
    {
        "text": "Somos gens da arte",
        "image": "",
        "key": 55
    },
    {
        "text": "Nada fazemos sem arte",
        "image": "",
        "key": 56
    },
    {
        "text": "O ativo verbo encarnado",
        "image": "",
        "key": 57
    },
    {
        "text": "Como nos fazemos",
        "image": "",
        "key": 58
    },
    {
        "text": "Nós mesmos outros",
        "image": "",
        "key": 59
    },
    {
        "text": "Sempre somos distintos",
        "image": "",
        "key": 60
    },
    {
        "text": "Candorosas aposições",
        "image": "",
        "key": 61
    },
    {
        "text": "Por dentro de cada um",
        "image": "",
        "key": 62
    },
    {
        "text": "Há muito mais todavia",
        "image": "",
        "key": 63
    },
    {
        "text": "Poeta de tantos nomes",
        "image": "",
        "key": 64
    },
    {
        "text": "Homem que és poeta",
        "image": "",
        "key": 65
    },
    {
        "text": "Matemático do universo",
        "image": "",
        "key": 66
    },
    {
        "text": "Adversidades superas",
        "image": "",
        "key": 67
    },
    {
        "text": "Superando-te a ti mesmo",
        "image": "",
        "key": 68
    },
    {
        "text": "É arte o que um faz",
        "image": "",
        "key": 69
    },
    {
        "text": "Quanto é o que passamos",
        "image": "",
        "key": 70
    },
    {
        "text": "Para hoje amar assim",
        "image": "",
        "key": 71
    },
    {
        "text": "E assim é como amamos",
        "image": "",
        "key": 72
    },
    {
        "text": "A vida em vidas",
        "image": "",
        "key": 73
    },
    {
        "text": "Tu e eu eles e todas elas",
        "image": "",
        "key": 74
    },
    {
        "text": "Todas as formas de vida",
        "image": "",
        "key": 75
    },
    {
        "text": "Formamos a vida mesma",
        "image": "",
        "key": 76
    },
    {
        "text": "As bocas da vida",
        "image": "",
        "key": 77
    },
    {
        "text": "Sou uma voz da vida",
        "image": "",
        "key": 78
    },
    {
        "text": "Uma de suas tantas vozes",
        "image": "",
        "key": 79
    },
    {
        "text": "Seres legíveis",
        "image": "",
        "key": 80
    },
    {
        "text": "Ao descobrí-los",
        "image": "",
        "key": 81
    },
    {
        "text": "Amigos do profundo",
        "image": "",
        "key": 82
    },
    {
        "text": "Tens que saber encotnrar",
        "image": "",
        "key": 83
    },
    {
        "text": "E ele mesmo nos demonstra",
        "image": "",
        "key": 84
    },
    {
        "text": "Que é matéria como tal",
        "image": "",
        "key": 85
    },
    {
        "text": "Como muitos ocos e total",
        "image": "",
        "key": 86
    },
    {
        "text": "Também partes de seu corpo",
        "image": "",
        "key": 87
    },
    {
        "text": "Oco que por oco algo é",
        "image": "",
        "key": 88
    },
    {
        "text": "Por si mesmo algo é",
        "image": "",
        "key": 89
    },
    {
        "text": "E um oco mesmo que é",
        "image": "",
        "key": 90
    },
    {
        "text": "Um oco dentro dum corpo",
        "image": "",
        "key": 91
    },
    {
        "text": "Símbolo matemático",
        "image": "",
        "key": 92
    },
    {
        "text": "Um oco há no meu corpo",
        "image": "",
        "key": 93
    },
    {
        "text": "Algo passa por ele",
        "image": "",
        "key": 94
    },
    {
        "text": "É o vento da vida",
        "image": "",
        "key": 95
    },
    {
        "text": "Vida é meu próprio oco",
        "image": "",
        "key": 96
    },
    {
        "text": "Vida em vidas Mãe de mães",
        "image": "",
        "key": 97
    },
    {
        "text": "É nossa mesma vida",
        "image": "",
        "key": 98
    },
    {
        "text": "Um amor de despedidas",
        "image": "",
        "key": 99
    },
    {
        "text": "Eternos renasceres",
        "image": "",
        "key": 100
    },
    {
        "text": "Um suspiro de prazeres",
        "image": "",
        "key": 101
    },
    {
        "text": "Um arroio Dançarino",
        "image": "",
        "key": 102
    },
    {
        "text": "Trampolim para adiante",
        "image": "",
        "key": 103
    },
    {
        "text": "Pontes sobre o tempo",
        "image": "",
        "key": 104
    },
    {
        "text": "Somos assim nós",
        "image": "",
        "key": 105
    },
    {
        "text": "Homens de pouca fé",
        "image": "",
        "key": 106
    },
    {
        "text": "E muita fidelidade",
        "image": "",
        "key": 107
    },
    {
        "text": "A palavra é uma graça",
        "image": "",
        "key": 108
    },
    {
        "text": "Cantar é o mais ligeiro",
        "image": "",
        "key": 109
    },
    {
        "text": "É eco do coração",
        "image": "",
        "key": 110
    },
    {
        "text": "Bramido do mar",
        "image": "",
        "key": 111
    },
    {
        "text": "Tempo de um só compasso",
        "image": "",
        "key": 112
    },
    {
        "text": "Reúnes todos os tempos",
        "image": "",
        "key": 113
    },
    {
        "text": "Uma nota é cada onda",
        "image": "",
        "key": 114
    },
    {
        "text": "Arroubamento venturoso",
        "image": "",
        "key": 115
    },
    {
        "text": "Infinito pentagrama",
        "image": "",
        "key": 116
    },
    {
        "text": "Anagramas que são notas",
        "image": "",
        "key": 117
    },
    {
        "text": "Sonidos que são corpos",
        "image": "",
        "key": 118
    },
    {
        "text": "Espaços que são cheios",
        "image": "",
        "key": 119
    },
    {
        "text": "Mar de toda a vida",
        "image": "",
        "key": 120
    },
    {
        "text": "Ondas de todos os mares",
        "image": "",
        "key": 121
    },
    {
        "text": "Rompendo incessantemente",
        "image": "",
        "key": 122
    },
    {
        "text": "Morre a tarde",
        "image": "",
        "key": 123
    },
    {
        "text": "Renasce no dia",
        "image": "",
        "key": 124
    },
    {
        "text": "Entretecida noite",
        "image": "",
        "key": 125
    },
    {
        "text": "Notas de cada canto",
        "image": "",
        "key": 126
    },
    {
        "text": "Como imensurável",
        "image": "",
        "key": 127
    },
    {
        "text": "Canto do mar dos mares",
        "image": "",
        "key": 128
    },
    {
        "text": "Se antecipa a aurora",
        "image": "",
        "key": 129
    },
    {
        "text": "Haverá meiodia",
        "image": "",
        "key": 130
    },
    {
        "text": "Assim seja um opúsculo",
        "image": "",
        "key": 131
    },
    {
        "text": "E crepúsculo meu",
        "image": "",
        "key": 132
    },
    {
        "text": "Um dia chegarás",
        "image": "",
        "key": 133
    },
    {
        "text": "Para que retorne",
        "image": "",
        "key": 134
    },
    {
        "text": "Somente em mim mesmo",
        "image": "",
        "key": 135
    },
    {
        "text": "Origem original",
        "image": "",
        "key": 136
    },
    {
        "text": "Viajeiro musical",
        "image": "",
        "key": 137
    },
    {
        "text": "Nós contemplamos",
        "image": "",
        "key": 138
    },
    {
        "text": "Por isso nos amamos",
        "image": "",
        "key": 139
    },
    {
        "text": "Assim como te amo",
        "image": "",
        "key": 140
    },
    {
        "text": "Não poderia deixar de amar-te",
        "image": "",
        "key": 141
    },
    {
        "text": "Sempre mais todavia",
        "image": "",
        "key": 142
    },
    {
        "text": "Me desvivo porque vivo",
        "image": "",
        "key": 143
    },
    {
        "text": "Te amo amor porque te sinto",
        "image": "",
        "key": 144
    },
    {
        "text": "Quero eu este tormento",
        "image": "",
        "key": 145
    },
    {
        "text": "Queimo-me com tanto amor",
        "image": "",
        "key": 146
    },
    {
        "text": "Luz e chama de fogo",
        "image": "",
        "key": 147
    },
    {
        "text": "É o amor desejado",
        "image": "",
        "key": 148
    },
    {
        "text": "De nós enamorados",
        "image": "",
        "key": 149
    },
    {
        "text": "A mesma vida que amamos",
        "image": "",
        "key": 150
    },
    {
        "text": "Como um louco apaixonado",
        "image": "",
        "key": 151
    },
    {
        "text": "Teu passado é meu passado",
        "image": "",
        "key": 152
    },
    {
        "text": "Sou um corpo de teu corpo",
        "image": "",
        "key": 153
    },
    {
        "text": "Teu futuro é meu futuro",
        "image": "",
        "key": 154
    },
    {
        "text": "Sou razão de sem razão",
        "image": "",
        "key": 155
    },
    {
        "text": "A loucura não razoa",
        "image": "",
        "key": 156
    },
    {
        "text": "E às vezes a raciocinamos",
        "image": "",
        "key": 157
    },
    {
        "text": "Sublime confirmação",
        "image": "",
        "key": 158
    },
    {
        "text": "Pegados da contemplação",
        "image": "",
        "key": 159
    },
    {
        "text": "Sempre junto dela",
        "image": "",
        "key": 160
    },
    {
        "text": "Por toda parte repartida",
        "image": "",
        "key": 161
    },
    {
        "text": "Adentro meu também",
        "image": "",
        "key": 162
    },
    {
        "text": "Por amar-te é que me amo",
        "image": "",
        "key": 163
    },
    {
        "text": "E te amo companheira",
        "image": "",
        "key": 164
    },
    {
        "text": "Te afirmo e me afirmas",
        "image": "",
        "key": 165
    },
    {
        "text": "E a vida nos reafirma",
        "image": "",
        "key": 166
    },
    {
        "text": "Reafirmações de vida",
        "image": "",
        "key": 167
    },
    {
        "text": "Vida de reafirmações",
        "image": "",
        "key": 168
    },
    {
        "text": "Nada fica e tudo passa",
        "image": "",
        "key": 169
    },
    {
        "text": "E à vez somos eternos",
        "image": "",
        "key": 170
    },
    {
        "text": "De revolução em revolução",
        "image": "",
        "key": 171
    },
    {
        "text": "Vivamente revolucionando-nos",
        "image": "",
        "key": 172
    },
    {
        "text": "Somente assim se modifica tudo",
        "image": "",
        "key": 173
    },
    {
        "text": "Permanecendo no modificado",
        "image": "",
        "key": 174
    },
    {
        "text": "Vamos juntos companheiros",
        "image": "",
        "key": 175
    },
    {
        "text": "Naufragando na deriva",
        "image": "",
        "key": 176
    },
    {
        "text": "No mar não há caminhos",
        "image": "",
        "key": 177
    },
    {
        "text": "Gargalhadas sobre a água",
        "image": "",
        "key": 178
    },
    {
        "text": "Transparente é o risco",
        "image": "",
        "key": 179
    },
    {
        "text": "E é por característica",
        "image": "",
        "key": 180
    },
    {
        "text": "Risadas entre dentes",
        "image": "",
        "key": 181
    },
    {
        "text": "Choramos para rir-nos",
        "image": "",
        "key": 182
    },
    {
        "text": "Sorrisos carregando lágrimas",
        "image": "",
        "key": 183
    },
    {
        "text": "Prazeres e sofrimentos",
        "image": "",
        "key": 184
    },
    {
        "text": "Lágrimas de risos",
        "image": "",
        "key": 185
    },
    {
        "text": "Vozes de canto",
        "image": "",
        "key": 186
    },
    {
        "text": "Colóquio universal",
        "image": "",
        "key": 187
    },
    {
        "text": "Somente vida é o canto",
        "image": "",
        "key": 188
    },
    {
        "text": "Simpatia o que sinto",
        "image": "",
        "key": 189
    },
    {
        "text": "Entusiasmo frenético",
        "image": "",
        "key": 190
    },
    {
        "text": "Vaporosas alucinações",
        "image": "",
        "key": 191
    },
    {
        "text": "Súbita desordem",
        "image": "",
        "key": 192
    },
    {
        "text": "Semelhantes singluaridades",
        "image": "",
        "key": 193
    },
    {
        "text": "Desiguais da multiplicidade",
        "image": "",
        "key": 194
    },
    {
        "text": "Temperadas afinidades e antipatias",
        "image": "",
        "key": 195
    },
    {
        "text": "Indistinto cada é de tudo",
        "image": "",
        "key": 196
    },
    {
        "text": "Improvisações de amores",
        "image": "",
        "key": 197
    },
    {
        "text": "Melodia indissolúvel",
        "image": "",
        "key": 198
    },
    {
        "text": "Retratos de autorretratos",
        "image": "",
        "key": 199
    },
    {
        "text": "Flores dum mesmo jardim",
        "image": "",
        "key": 200
    },
    {
        "text": "Jardim de invernos e primaveras",
        "image": "",
        "key": 201
    },
    {
        "text": "Somos pólem para outros",
        "image": "",
        "key": 202
    },
    {
        "text": "E pólem tiramos de outros",
        "image": "",
        "key": 203
    },
    {
        "text": "De mel é nossa oferenda",
        "image": "",
        "key": 204
    },
    {
        "text": "A colméia é nosso gênero",
        "image": "",
        "key": 205
    },
    {
        "text": "Geléia da natureza",
        "image": "",
        "key": 206
    },
    {
        "text": "Somos nós poetas",
        "image": "",
        "key": 207
    },
    {
        "text": "Artistas que fazem mel",
        "image": "",
        "key": 208
    },
    {
        "text": "Adoçando a vida",
        "image": "",
        "key": 209
    },
    {
        "text": "Doce me sabe tua boca",
        "image": "",
        "key": 210
    },
    {
        "text": "Quanto ouro em teus cabelos",
        "image": "",
        "key": 211
    },
    {
        "text": "Invernos por teus olhos",
        "image": "",
        "key": 212
    },
    {
        "text": "Pestanejos disparando",
        "image": "",
        "key": 213
    },
    {
        "text": "Ventos de vozes dispersas",
        "image": "",
        "key": 214
    },
    {
        "text": "Febre de todo sexo",
        "image": "",
        "key": 215
    },
    {
        "text": "Pétalas são meus dedos",
        "image": "",
        "key": 216
    },
    {
        "text": "Uma flor em cada mão",
        "image": "",
        "key": 217
    },
    {
        "text": "Uma rama em cada braço",
        "image": "",
        "key": 218
    },
    {
        "text": "No tronco medular",
        "image": "",
        "key": 219
    },
    {
        "text": "As raízes são os pés",
        "image": "",
        "key": 220
    },
    {
        "text": "Afundados na terra mãe",
        "image": "",
        "key": 221
    },
    {
        "text": "Passeantes de universo",
        "image": "",
        "key": 222
    },
    {
        "text": "Filhos da existência",
        "image": "",
        "key": 223
    },
    {
        "text": "Filhos da mesma mãe",
        "image": "",
        "key": 224
    },
    {
        "text": "Mãe de todos os filhos",
        "image": "",
        "key": 225
    },
    {
        "text": "Brincando com vida na vida",
        "image": "",
        "key": 226
    },
    {
        "text": "Me afirmo em toda tirada",
        "image": "",
        "key": 227
    },
    {
        "text": "Rodam os dados do azar",
        "image": "",
        "key": 228
    },
    {
        "text": "Para cair na terra",
        "image": "",
        "key": 229
    },
    {
        "text": "Raízes dalgum torrão",
        "image": "",
        "key": 230
    },
    {
        "text": "Quiméricas plumas imaginárias",
        "image": "",
        "key": 231
    },
    {
        "text": "E qual pétalas caímos",
        "image": "",
        "key": 232
    },
    {
        "text": "Bomboleiam tantas coisas",
        "image": "",
        "key": 233
    },
    {
        "text": "Estremecedora é a vida",
        "image": "",
        "key": 234
    },
    {
        "text": "Inquietante movimento",
        "image": "",
        "key": 235
    },
    {
        "text": "Luzes de todos os momentos",
        "image": "",
        "key": 236
    },
    {
        "text": "Menino de todos lugares",
        "image": "",
        "key": 237
    },
    {
        "text": "Esperança e novamente",
        "image": "",
        "key": 238
    },
    {
        "text": "Arreando loucura",
        "image": "",
        "key": 239
    },
    {
        "text": "Um poema de colcheias",
        "image": "",
        "key": 240
    },
    {
        "text": "Um poema mãe",
        "image": "",
        "key": 241
    },
    {
        "text": "De todos os poemas",
        "image": "",
        "key": 242
    },
    {
        "text": "Poema de toda mãe",
        "image": "",
        "key": 243
    },
    {
        "text": "Rosa de toda rosa",
        "image": "",
        "key": 244
    },
    {
        "text": "Espinho de todo talo",
        "image": "",
        "key": 245
    },
    {
        "text": "Amigos da amizade",
        "image": "",
        "key": 246
    },
    {
        "text": "Amor sem rivalidade",
        "image": "",
        "key": 247
    },
    {
        "text": "Amigos entre amigos",
        "image": "",
        "key": 248
    },
    {
        "text": "Cinzas que se reavivam",
        "image": "",
        "key": 249
    },
    {
        "text": "Vamos queimando-nos e queimando",
        "image": "",
        "key": 250
    },
    {
        "text": "Arde toda a existência",
        "image": "",
        "key": 251
    },
    {
        "text": "Sensação estrutural",
        "image": "",
        "key": 252
    },
    {
        "text": "Onde tudo se consome",
        "image": "",
        "key": 253
    },
    {
        "text": "Onde tudo se reaviva",
        "image": "",
        "key": 254
    },
    {
        "text": "Não precisamos abrigos",
        "image": "",
        "key": 255
    },
    {
        "text": "Podemos morrer de frio",
        "image": "",
        "key": 256
    },
    {
        "text": "Nascemos a cada instante",
        "image": "",
        "key": 257
    },
    {
        "text": "Entre gelos e fogos vivos",
        "image": "",
        "key": 258
    },
    {
        "text": "Perpetuamente acendidos",
        "image": "",
        "key": 259
    },
    {
        "text": "No momento de todas as luzes",
        "image": "",
        "key": 260
    },
    {
        "text": "Somos uma só vela",
        "image": "",
        "key": 261
    },
    {
        "text": "E filosofando a criação",
        "image": "",
        "key": 262
    },
    {
        "text": "Saltando de onda em onda",
        "image": "",
        "key": 263
    },
    {
        "text": "Delirando a ilusão",
        "image": "",
        "key": 264
    },
    {
        "text": "Extraviados e com inspiração",
        "image": "",
        "key": 265
    },
    {
        "text": "No romance da procriação",
        "image": "",
        "key": 266
    },
    {
        "text": "E cor e perfume e sabor",
        "image": "",
        "key": 267
    },
    {
        "text": "Melancolia em ultramar",
        "image": "",
        "key": 268
    },
    {
        "text": "Velas que ardem navegando",
        "image": "",
        "key": 269
    },
    {
        "text": "Até um rumo desconhecido",
        "image": "",
        "key": 270
    },
    {
        "text": "Aflição que passa sempre",
        "image": "",
        "key": 271
    },
    {
        "text": "Afundada na vida",
        "image": "",
        "key": 272
    },
    {
        "text": "Espírito de matéria",
        "image": "",
        "key": 273
    },
    {
        "text": "Idéia de matéria",
        "image": "",
        "key": 274
    },
    {
        "text": "Pensamento material",
        "image": "",
        "key": 275
    },
    {
        "text": "Mente cósmica",
        "image": "",
        "key": 276
    },
    {
        "text": "Cósmico espírito",
        "image": "",
        "key": 277
    },
    {
        "text": "Ardores de um grande coração",
        "image": "",
        "key": 278
    },
    {
        "text": "Ritmos de taquicardias",
        "image": "",
        "key": 279
    },
    {
        "text": "Coroa de amapolas",
        "image": "",
        "key": 280
    },
    {
        "text": "Bolas de sóis de ouro",
        "image": "",
        "key": 281
    },
    {
        "text": "Filigranas fundidas",
        "image": "",
        "key": 282
    },
    {
        "text": "Zumbindo ao vento",
        "image": "",
        "key": 283
    },
    {
        "text": "Girassol de todo sol",
        "image": "",
        "key": 284
    },
    {
        "text": "Companheiro desta viagem",
        "image": "",
        "key": 285
    },
    {
        "text": "Tirar-se é arriscar",
        "image": "",
        "key": 286
    },
    {
        "text": "Tudo pelo desejado",
        "image": "",
        "key": 287
    },
    {
        "text": "Ressaltamos continuamente",
        "image": "",
        "key": 288
    },
    {
        "text": "Quebrando e quebrando-nos",
        "image": "",
        "key": 289
    },
    {
        "text": "Talhamos nós mesmos",
        "image": "",
        "key": 290
    },
    {
        "text": "Nosso corpo e pensamento",
        "image": "",
        "key": 291
    },
    {
        "text": "Nossa obra somos nós",
        "image": "",
        "key": 292
    },
    {
        "text": "Passo nosso pela vida",
        "image": "",
        "key": 293
    },
    {
        "text": "O tempo borra as pegadas",
        "image": "",
        "key": 294
    },
    {
        "text": "E que não borra o tempo",
        "image": "",
        "key": 295
    },
    {
        "text": "Nós dele nos borramos",
        "image": "",
        "key": 296
    },
    {
        "text": "Como tempos do tempo",
        "image": "",
        "key": 297
    },
    {
        "text": "Divinos momentos momentâneos",
        "image": "",
        "key": 298
    },
    {
        "text": "Cúmulos de remoinhos",
        "image": "",
        "key": 299
    },
    {
        "text": "Vida de tempo",
        "image": "",
        "key": 300
    },
    {
        "text": "Contemporâneo de vida",
        "image": "",
        "key": 301
    },
    {
        "text": "Contemporâneos do tempo",
        "image": "",
        "key": 302
    },
    {
        "text": "Vamos para voltar a ser",
        "image": "",
        "key": 303
    },
    {
        "text": "Enfilados buracos",
        "image": "",
        "key": 304
    },
    {
        "text": "Diamantes encolarados",
        "image": "",
        "key": 305
    },
    {
        "text": "Os lados de todas partes",
        "image": "",
        "key": 306
    },
    {
        "text": "A cada momento florescendo",
        "image": "",
        "key": 307
    },
    {
        "text": "Flauta flautista dor e amor",
        "image": "",
        "key": 308
    },
    {
        "text": "Potencialmente o rumor",
        "image": "",
        "key": 309
    },
    {
        "text": "Em todas suas vontades",
        "image": "",
        "key": 310
    },
    {
        "text": "Todas são suas verdades",
        "image": "",
        "key": 311
    },
    {
        "text": "A vida sim que é verdade",
        "image": "",
        "key": 312
    },
    {
        "text": "A verdadeira mentira",
        "image": "",
        "key": 313
    },
    {
        "text": "A morte é a vida mesma",
        "image": "",
        "key": 314
    },
    {
        "text": "Nós que não morremos",
        "image": "",
        "key": 315
    },
    {
        "text": "Amanhã nos separaremos",
        "image": "",
        "key": 316
    },
    {
        "text": "No ocaso sem fim",
        "image": "",
        "key": 317
    },
    {
        "text": "Evolução e involução",
        "image": "",
        "key": 318
    },
    {
        "text": "Como partes da vida",
        "image": "",
        "key": 319
    },
    {
        "text": "Erros substanciais",
        "image": "",
        "key": 320
    },
    {
        "text": "Sucumbem instantaneamente",
        "image": "",
        "key": 321
    },
    {
        "text": "Afãs distraídos",
        "image": "",
        "key": 322
    },
    {
        "text": "Transfigurada mentira",
        "image": "",
        "key": 323
    },
    {
        "text": "Indeterminável é muito",
        "image": "",
        "key": 324
    },
    {
        "text": "Em todos os estados",
        "image": "",
        "key": 325
    },
    {
        "text": "Tão belos como grosseiros",
        "image": "",
        "key": 326
    },
    {
        "text": "No informado e na forma",
        "image": "",
        "key": 327
    },
    {
        "text": "Sendo um e todo",
        "image": "",
        "key": 328
    },
    {
        "text": "Argola matrimonial",
        "image": "",
        "key": 329
    },
    {
        "text": "Em fisioquímicos carnavais",
        "image": "",
        "key": 330
    },
    {
        "text": "Devindo azares",
        "image": "",
        "key": 331
    },
    {
        "text": "No excepcional caos",
        "image": "",
        "key": 332
    },
    {
        "text": "Vermos e adjetivos",
        "image": "",
        "key": 333
    },
    {
        "text": "Coisas adentro de coisas",
        "image": "",
        "key": 334
    },
    {
        "text": "Atômicas carambolas",
        "image": "",
        "key": 335
    },
    {
        "text": "Contradição diferencial",
        "image": "",
        "key": 336
    },
    {
        "text": "Oníricas paixões",
        "image": "",
        "key": 337
    },
    {
        "text": "Melodioso estupefaciente",
        "image": "",
        "key": 338
    },
    {
        "text": "Pletórica onipotência",
        "image": "",
        "key": 339
    },
    {
        "text": "Ininteligível soberbia",
        "image": "",
        "key": 340
    },
    {
        "text": "Excelsa causalidade",
        "image": "",
        "key": 341
    },
    {
        "text": "Magnificente conversão",
        "image": "",
        "key": 342
    },
    {
        "text": "Constante movimento e transição",
        "image": "",
        "key": 343
    },
    {
        "text": "Viver é um prazer",
        "image": "",
        "key": 344
    },
    {
        "text": "Estando onde estejam",
        "image": "",
        "key": 345
    },
    {
        "text": "Vivendo na vida em vidas",
        "image": "",
        "key": 346
    },
    {
        "text": "O gozo é por viver",
        "image": "",
        "key": 347
    },
    {
        "text": "Inacabadamente em tudo",
        "image": "",
        "key": 348
    },
    {
        "text": "A duração infinita",
        "image": "",
        "key": 349
    },
    {
        "text": "A revolução permanente",
        "image": "",
        "key": 350
    },
    {
        "text": "Serpe devoradora de si",
        "image": "",
        "key": 351
    },
    {
        "text": "Se enrosca para dentro",
        "image": "",
        "key": 352
    },
    {
        "text": "A cola sempre estirando-se",
        "image": "",
        "key": 353
    },
    {
        "text": "Círculo e circuito",
        "image": "",
        "key": 354
    },
    {
        "text": "Anel tempestuoso",
        "image": "",
        "key": 355
    },
    {
        "text": "Eterno himeneu",
        "image": "",
        "key": 356
    },
    {
        "text": "Entre tua cola e tua boca",
        "image": "",
        "key": 357
    },
    {
        "text": "Entre matéria e espírito",
        "image": "",
        "key": 358
    },
    {
        "text": "Tudo entre as plumas",
        "image": "",
        "key": 359
    },
    {
        "text": "Pleniluniando sua sorte",
        "image": "",
        "key": 360
    },
    {
        "text": "Intrínseco encadeamento",
        "image": "",
        "key": 361
    },
    {
        "text": "Rosário de um só poema",
        "image": "",
        "key": 362
    },
    {
        "text": "Poemário vivente",
        "image": "",
        "key": 363
    },
    {
        "text": "Música sempre viva",
        "image": "",
        "key": 364
    },
    {
        "text": "É algo do amor",
        "image": "",
        "key": 365
    },
    {
        "text": "De todo enamorado",
        "image": "",
        "key": 366
    }
]